Homework-2/TCL, Verilog Scripts/mux_comparator.v
module mux_comparator (
    input [2:0] x,
    input [2:0] y,
    output reg [2:0] z
    );

    always @(x or y) 
    begin

      if (x < y) 
        z = x; 

      else 
        z = y;
      
    end
    
endmodule

Homework-2/TCL, Verilog Scripts/mux_comparator_tb.v
//Testbench for the mux_comparator
`timescale 1ns/1ns
`include "mux_comparator.v"

module mux_comparator_tb;

    // declaring inputs
    reg [2:0] x;
    reg [2:0] y;
    wire [2:0] z;

    // Instantiate the Unit Under Test (UUT)
    mux_comparator uut (.x(x),.y(y),.z(z));

    initial begin
	//for creating vcd waveform file to view in gtkwave
	
	$dumpfile ("mux_comparator.vcd"); 
	$dumpvars(0, mux_comparator_tb);

        // Applying inputs
        x = 0;
        y = 0;

        #20;
        
        //some of the cases to verify the working of the mux_comparator
        x = 3;     y = 0;      #10;    $write(" x value = "); $write(x); $write(" , y value = "); $write(y); $write(" --> z value = "); $display(z);
        x = 4;     y = 1;      #10;    $write(" x value = "); $write(x); $write(" , y value = "); $write(y); $write(" --> z value = "); $display(z);
        x = 1;     y = 2;      #10;    $write(" x value = "); $write(x); $write(" , y value = "); $write(y); $write(" --> z value = "); $display(z);
        x = 4;     y = 4;      #10;    $write(" x value = "); $write(x); $write(" , y value = "); $write(y); $write(" --> z value = "); $display(z);
        x = 1;     y = 0;      #10;    $write(" x value = "); $write(x); $write(" , y value = "); $write(y); $write(" --> z value = "); $display(z);
        x = 6;     y = 5;      #10;    $write(" x value = "); $write(x); $write(" , y value = "); $write(y); $write(" --> z value = "); $display(z);
        x = 4;     y = 6;      #10;    $write(" x value = "); $write(x); $write(" , y value = "); $write(y); $write(" --> z value = "); $display(z);
        x = 6;     y = 3;      #10;    $write(" x value = "); $write(x); $write(" , y value = "); $write(y); $write(" --> z value = "); $display(z);

    end
      
endmodule

Homework-2/TCL, Verilog Scripts/mux_comparator.vcd
$date
	Sun Sep 26 19:32:50 2021
$end
$version
	Icarus Verilog
$end
$timescale
	1ns
$end
$scope module mux_comparator_tb $end
$var wire 3 ! z [2:0] $end
$var reg 3 " x [2:0] $end
$var reg 3 # y [2:0] $end
$scope module uut $end
$var wire 3 $ x [2:0] $end
$var wire 3 % y [2:0] $end
$var reg 3 & z [2:0] $end
$upscope $end
$upscope $end
$enddefinitions $end
#0
$dumpvars
b0 &
b0 %
b0 $
b0 #
b0 "
b0 !
$end
#20
b11 "
b11 $
#30
b1 !
b1 &
b1 #
b1 %
b100 "
b100 $
#40
b10 #
b10 %
b1 "
b1 $
#50
b100 !
b100 &
b100 #
b100 %
b100 "
b100 $
#60
b0 !
b0 &
b0 #
b0 %
b1 "
b1 $
#70
b101 !
b101 &
b101 #
b101 %
b110 "
b110 $
#80
b100 !
b100 &
b110 #
b110 %
b100 "
b100 $
#90
b11 !
b11 &
b11 #
b11 %
b110 "
b110 $
